compassone_sdk/__init__.py
compassone_sdk/api/__init__.py
compassone_sdk/api/account/__init__.py
compassone_sdk/api/account/get_account_controller.py
compassone_sdk/api/account/get_account_controller_list.py
compassone_sdk/api/cloud_mdr/__init__.py
compassone_sdk/api/cloud_mdr/delete_remove_approved_country.py
compassone_sdk/api/cloud_mdr/delete_remove_approved_country_for_user.py
compassone_sdk/api/cloud_mdr/get_approved_countries.py
compassone_sdk/api/cloud_mdr/get_country_by_code.py
compassone_sdk/api/cloud_mdr/get_list_approved_countries_for_user.py
compassone_sdk/api/cloud_mdr/get_list_countries.py
compassone_sdk/api/cloud_mdr/get_list_users.py
compassone_sdk/api/cloud_mdr/post_approve_country_for_user.py
compassone_sdk/api/cloud_mdr/put_approve_country.py
compassone_sdk/api/cloud_mdr_cisco/__init__.py
compassone_sdk/api/cloud_mdr_cisco/delete_cisco_onboarding.py
compassone_sdk/api/cloud_mdr_cisco/get_cisco_onboarding_by_id.py
compassone_sdk/api/cloud_mdr_cisco/get_list_cisco_onboardings.py
compassone_sdk/api/cloud_mdr_cisco/post_complete_cisco_onboarding.py
compassone_sdk/api/cloud_mdr_cisco/post_create_cisco_onboarding.py
compassone_sdk/api/cloud_mdr_cisco/post_sync_cisco_users.py
compassone_sdk/api/cloud_mdr_google/__init__.py
compassone_sdk/api/cloud_mdr_google/get_google_onboarding_by_id.py
compassone_sdk/api/cloud_mdr_google/get_list_google_onboardings.py
compassone_sdk/api/cloud_mdr_m365/__init__.py
compassone_sdk/api/cloud_mdr_m365/delete_remove_approved_country_for_m365_user.py
compassone_sdk/api/cloud_mdr_m365/delete_remove_m365_approved_country.py
compassone_sdk/api/cloud_mdr_m365/get_connection_by_id.py
compassone_sdk/api/cloud_mdr_m365/get_list_approved_countries.py
compassone_sdk/api/cloud_mdr_m365/get_list_approved_countries_for_m365_user.py
compassone_sdk/api/cloud_mdr_m365/get_list_m365_users.py
compassone_sdk/api/cloud_mdr_m365/get_tenant_by_id.py
compassone_sdk/api/cloud_mdr_m365/post_approve_country_for_m365_user.py
compassone_sdk-0.0.60.dist-info/METADATA
compassone_sdk-0.0.60.dist-info/WHEEL
compassone_sdk-0.0.60.dist-info/RECORD
